geomulticorr/__init__.py
geomulticorr/geomorph.py
geomulticorr/pair.py
geomulticorr/pzone.py
geomulticorr/session.py
geomulticorr/spine.py
geomulticorr/thumb.py
geomulticorr/xzone.py
geomulticorr/resources/map_styles/vector-field_style_1.qml
geomulticorr/resources/project_template/geodatabase_template-project.gpkg
geomulticorr/resources/project_template/map_template-project.qgz
geomulticorr-0.2.2.dist-info/METADATA
geomulticorr-0.2.2.dist-info/WHEEL
geomulticorr-0.2.2.dist-info/licenses/LICENSE.md
geomulticorr-0.2.2.dist-info/RECORD
