Metadata-Version: 2.1
Name: geomulticorr
Version: 0.2.2
Summary: A python lib to study earth-surface displacements from optical images with Ames Stereo Pipeline
Author-email: Thibaut Duvanel <thibaut.duvanel@univ-smb.fr>
License-File: LICENSE.md
Classifier: License :: OSI Approved :: MIT License
Classifier: Operating System :: OS Independent
Classifier: Programming Language :: Python :: 3
Requires-Python: >=3.10
